crapi/LICENSE.txt
crapi/README.md
crapi/README.rst
crapi/__init__.py
crapi/requirements.txt
crapi/ipc/ClientPipe.py
crapi/ipc/Pipe.py
crapi/ipc/PipeError.py
crapi/ipc/PipeTimeoutError.py
crapi/ipc/ServerPipe.py
crapi/ipc/__init__.py
crapi/misc/Utils.py
crapi/misc/__init__.py
crapi/service/Daemon.py
crapi/service/DaemonContractError.py
crapi/service/DaemonError.py
crapi/service/DaemonNamingError.py
crapi/service/DaemonPrivilegeException.py
crapi/service/DaemonTimeoutError.py
crapi/service/WindowsDaemonFactory.py
crapi/service/WindowsDaemonTemplate.tmpl
crapi/service/__init__.py
crapi/service/management/Administrator.py
crapi/service/management/Supervisor.py
crapi/service/management/__init__.py
crapi/service/rt/__init__.py
crapi-0.0.2b5.dist-info/DESCRIPTION.rst
crapi-0.0.2b5.dist-info/METADATA
crapi-0.0.2b5.dist-info/RECORD
crapi-0.0.2b5.dist-info/WHEEL
crapi-0.0.2b5.dist-info/metadata.json
crapi-0.0.2b5.dist-info/top_level.txt
