Metadata-Version: 2.0
Name: crapi
Version: 0.0.2b5
Summary: CRAPI: Common Range API
Home-page: https://github.com/kounavi/crapi
Author: Iraklis D., Kritonas P.
Author-email: hdiakos@outlook.com, kriton_pilavidis@outlook.com
License: ASF 2.0
Keywords: backend systems development wrapper pipes services daemons
Platform: windows
Platform: linux
Platform: server
Platform: workstation
Classifier: Development Status :: 4 - Beta
Classifier: Intended Audience :: Developers
Classifier: Intended Audience :: Information Technology
Classifier: Intended Audience :: Science/Research
Classifier: Topic :: Software Development :: Libraries :: Application Frameworks
Classifier: License :: OSI Approved :: Apache Software License
Classifier: Programming Language :: Python :: 2
Classifier: Programming Language :: Python :: 2.6
Classifier: Programming Language :: Python :: 2.7
Classifier: Operating System :: Microsoft
Classifier: Operating System :: POSIX :: Linux
Requires-Dist: MarkupSafe (==0.23)
Requires-Dist: enum34 (==1.1.1)
Requires-Dist: future (==0.15.2)
Requires-Dist: jinja2 (==2.8)
Provides-Extra: linux2
Provides-Extra: win32
Requires-Dist: pywin32 (==220); extra == 'win32'
